icatpackagemanager/__init__.py
icatpackagemanager/__main__.py
icatpackagemanager/cli.py
icatpackagemanager/commands.py
icatpackagemanager/files.py
icatpackagemanager/repo.py
icatpackagemanager/utils.py
icat_package_manager-0.0.6.dist-info/METADATA
icat_package_manager-0.0.6.dist-info/WHEEL
icat_package_manager-0.0.6.dist-info/entry_points.txt
icat_package_manager-0.0.6.dist-info/top_level.txt
icat_package_manager-0.0.6.dist-info/RECORD
