Metadata-Version: 2.1
Name: icat-package-manager
Version: 0.0.6
Summary: A CLI tool for automating installation of ICAT components
Author-email: Will Taylor <william.h.taylor@stfc.ac.uk>
License: Apache License 2.0
Project-URL: Homepage, https://github.com/WHTaylor/icat-package-manager
Project-URL: Repository, https://github.com/WHTaylor/icat-package-manager
Requires-Dist: lxml
